{
  "id": "spotlight-reveal-input",
  "name": "spotlight-reveal-input",
  "title": "Spotlight reveal and input",
  "description": "",
  "status": "completed",
  "dev_type": null,
  "scope": null,
  "package": "web",
  "priority": "P2",
  "creator": "webmatch3",
  "assignee": "webmatch3",
  "createdAt": "2026-07-21",
  "completedAt": "2026-07-21",
  "branch": null,
  "base_branch": "main",
  "worktree_path": null,
  "commit": null,
  "pr_url": null,
  "subtasks": [],
  "children": [],
  "parent": "07-21-spotlight-hide-and-seek",
  "relatedFiles": [],
  "notes": "",
  "meta": {}
}